AUTHORS.txt
LICENSE
LICENSE.md
MANIFEST.in
README.md
setup.py
l2rpn_baselines/__init__.py
l2rpn_baselines.egg-info/PKG-INFO
l2rpn_baselines.egg-info/SOURCES.txt
l2rpn_baselines.egg-info/dependency_links.txt
l2rpn_baselines.egg-info/not-zip-safe
l2rpn_baselines.egg-info/requires.txt
l2rpn_baselines.egg-info/top_level.txt
l2rpn_baselines/AsynchronousActorCritic/Action_reduced_list.py
l2rpn_baselines/AsynchronousActorCritic/ActorCritic_Agent.py
l2rpn_baselines/AsynchronousActorCritic/AsynchronousActorCritic.py
l2rpn_baselines/AsynchronousActorCritic/Runner.py
l2rpn_baselines/AsynchronousActorCritic/__init__.py
l2rpn_baselines/AsynchronousActorCritic/evaluate.py
l2rpn_baselines/AsynchronousActorCritic/run_grid2viz.py
l2rpn_baselines/AsynchronousActorCritic/train.py
l2rpn_baselines/AsynchronousActorCritic/user_environment_make.py
l2rpn_baselines/CurriculumAgent/__init__.py
l2rpn_baselines/CurriculumAgent/baseline.py
l2rpn_baselines/CurriculumAgent/evaluate.py
l2rpn_baselines/CurriculumAgent/train.py
l2rpn_baselines/DeepQSimple/__init__.py
l2rpn_baselines/DeepQSimple/deepQSimple.py
l2rpn_baselines/DeepQSimple/deepQ_NN.py
l2rpn_baselines/DeepQSimple/deepQ_NNParam.py
l2rpn_baselines/DeepQSimple/evaluate.py
l2rpn_baselines/DeepQSimple/train.py
l2rpn_baselines/DoNothing/__init__.py
l2rpn_baselines/DoNothing/doNothing.py
l2rpn_baselines/DoNothing/eval_donothing.py
l2rpn_baselines/DoNothing/main.py
l2rpn_baselines/DoubleDuelingDQN/__init__.py
l2rpn_baselines/DoubleDuelingDQN/doubleDuelingDQN.py
l2rpn_baselines/DoubleDuelingDQN/doubleDuelingDQNConfig.py
l2rpn_baselines/DoubleDuelingDQN/doubleDuelingDQN_NN.py
l2rpn_baselines/DoubleDuelingDQN/evaluate.py
l2rpn_baselines/DoubleDuelingDQN/inspect_action_space.py
l2rpn_baselines/DoubleDuelingDQN/prioritized_replay_buffer.py
l2rpn_baselines/DoubleDuelingDQN/segment_tree.py
l2rpn_baselines/DoubleDuelingDQN/train.py
l2rpn_baselines/DoubleDuelingRDQN/__init__.py
l2rpn_baselines/DoubleDuelingRDQN/doubleDuelingRDQN.py
l2rpn_baselines/DoubleDuelingRDQN/doubleDuelingRDQNConfig.py
l2rpn_baselines/DoubleDuelingRDQN/doubleDuelingRDQN_NN.py
l2rpn_baselines/DoubleDuelingRDQN/evaluate.py
l2rpn_baselines/DoubleDuelingRDQN/experienceBuffer.py
