Metadata-Version: 2.1
Name: l2rpn-baselines
Version: 0.8.0
Summary: L2RPN Baselines a repository to host baselines for l2rpn competitions.
Home-page: https://github.com/rte-france/L2RPN_Baselines
Author: Benjamin DONNOT
Author-email: benjamin.donnot@rte-france.com
License: MPL
Keywords: ML powergrid optmization RL power-systems
Classifier: Development Status :: 4 - Beta
Classifier: Programming Language :: Python :: 3.7
Classifier: Programming Language :: Python :: 3.8
Classifier: Programming Language :: Python :: 3.9
Classifier: Programming Language :: Python :: 3.10
Classifier: License :: OSI Approved :: Mozilla Public License 2.0 (MPL 2.0)
Classifier: Intended Audience :: Developers
Classifier: Intended Audience :: Education
Classifier: Intended Audience :: Science/Research
Classifier: Natural Language :: English
Provides-Extra: docs
Provides-Extra: optional
Provides-Extra: PPO_RLLIB
Provides-Extra: PPO_SB3
Provides-Extra: CurriculumAgent
License-File: LICENSE
License-File: LICENSE.md
License-File: AUTHORS.txt
